riggerlib/__init__.py
riggerlib/client.py
riggerlib/plugins.py
riggerlib/server.py
riggerlib/task.py
riggerlib/tools.py
riggerlib/wsgi.py
riggerlib-3.1.6.dist-info/LICENSE
riggerlib-3.1.6.dist-info/METADATA
riggerlib-3.1.6.dist-info/WHEEL
riggerlib-3.1.6.dist-info/pbr.json
riggerlib-3.1.6.dist-info/top_level.txt
riggerlib-3.1.6.dist-info/RECORD
