Metadata-Version: 2.1
Name: riggerlib
Version: 3.1.6
Summary: An event hook framework
Home-page: https://github.com/psav/riggerlib
Author: Pete Savage, Sean Myers, Milan Falesnik
Author-email: UNKNOWN
License: MIT
Keywords: event,linux,hook
Platform: UNKNOWN
Classifier: Programming Language :: Python
Classifier: Development Status :: 4 - Beta
Classifier: Operating System :: POSIX :: Linux
Classifier: License :: OSI Approved :: MIT License
Requires-Dist: funcsigs
Requires-Dist: pyzmq
Requires-Dist: pyyaml
Requires-Dist: six
